gxl_portal_gun/__init__.py
gxl_portal_gun/__main__.py
gxl_portal_gun/main.py
gxl_portal_gun-0.2.0.dist-info/METADATA
gxl_portal_gun-0.2.0.dist-info/WHEEL
gxl_portal_gun-0.2.0.dist-info/entry_points.txt
gxl_portal_gun-0.2.0.dist-info/RECORD
