Metadata-Version: 2.3
Name: gxl-portal-gun
Version: 0.2.0
Summary: 
Author: udo-bit
Author-email: enote_gxl@163.com
Requires-Python: >=3.12
Classifier: Programming Language :: Python :: 3
Classifier: Programming Language :: Python :: 3.12
Classifier: Programming Language :: Python :: 3.13
Requires-Dist: pandas (>=2.3.0,<3.0.0)
Requires-Dist: typer (>=0.16.0,<0.17.0)
